p621/__init__.py
p621/login.py
p621/requests.py
p621/posts/__init__.py
p621/posts/classes.py
p621/posts/interactions.py
p621-0.2.0.dist-info/METADATA
p621-0.2.0.dist-info/WHEEL
p621-0.2.0.dist-info/licenses/LICENSE
p621-0.2.0.dist-info/RECORD
