Metadata-Version: 2.3
Name: p621
Version: 0.2.0
Summary: an oversimplified wrapper and interactivity for the e621 API
Project-URL: Documentation, https://ideatsomefish.github.io/p621-documentation
Project-URL: Source, https://github.com/IdEatSomeFish/p621
Author-email: I'd Eat Some Fish <ideatsomefish@gmail.com>
License-File: LICENSE
Classifier: License :: OSI Approved :: MIT License
Classifier: Operating System :: OS Independent
Classifier: Programming Language :: Python :: 3
Requires-Python: >=3
Requires-Dist: requests
